airflow_dbt/__init__.py
airflow_dbt/__version__.py
airflow_dbt/hooks/__init__.py
airflow_dbt/hooks/dbt_hook.py
airflow_dbt/operators/__init__.py
airflow_dbt/operators/dbt_operator.py
airflow_dbt_winwin-0.5.15.dist-info/LICENSE.txt
airflow_dbt_winwin-0.5.15.dist-info/METADATA
airflow_dbt_winwin-0.5.15.dist-info/WHEEL
airflow_dbt_winwin-0.5.15.dist-info/top_level.txt
airflow_dbt_winwin-0.5.15.dist-info/RECORD
